rocket_args/__init__.py
rocket_args/main.py
rocket_args/utils.py
rocket_args-0.1.0.dist-info/LICENSE
rocket_args-0.1.0.dist-info/WHEEL
rocket_args-0.1.0.dist-info/METADATA
rocket_args-0.1.0.dist-info/RECORD
