Metadata-Version: 2.1
Name: rocket-args
Version: 0.1.0
Summary: Make your arg parsing even more declarative!
Home-page: https://github.com/Xaaq/Rocket-args
License: MIT
Author: Amadeusz Hercog
Author-email: xaaq333@gmail.com
Requires-Python: >=3.6,<4.0
Classifier: License :: OSI Approved :: MIT License
Classifier: Programming Language :: Python :: 3
Classifier: Programming Language :: Python :: 3.6
Classifier: Programming Language :: Python :: 3.7
Classifier: Programming Language :: Python :: 3.8
Project-URL: Documentation, https://xaaq.github.io/Rocket-args
Project-URL: Repository, https://github.com/Xaaq/Rocket-args
